topsis/topsis.py
topsis_anurag_101703088-1.0.1.dist-info/METADATA
topsis_anurag_101703088-1.0.1.dist-info/RECORD
topsis_anurag_101703088-1.0.1.dist-info/WHEEL
topsis_anurag_101703088-1.0.1.dist-info/entry_points.txt
topsis_anurag_101703088-1.0.1.dist-info/top_level.txt
