Metadata-Version: 2.1
Name: topsis-anurag-101703088
Version: 1.0.1
Summary: A Python package to choose the best alternative from a finite set of decision alternatives.
Home-page: https://github.com/Anurag-Aggarwal/101703088-topsis/blob/master/topsis.py
Author: Anurag Aggarwal
Author-email: agrawalanurag321@gmail.com
License: MIT
Platform: UNKNOWN
Classifier: License :: OSI Approved :: MIT License
Classifier: Programming Language :: Python :: 3
Classifier: Programming Language :: Python :: 3.7
Requires-Dist: sys
Requires-Dist: os
Requires-Dist: pandas
Requires-Dist: math
Requires-Dist: numpy
